pymagotchi/__init__.py
pymagotchi/__main__.py
pymagotchi/constants.py
pymagotchi/names.py
pymagotchi/pet.py
pymagotchi-1.1.0.dist-info/LICENSE
pymagotchi-1.1.0.dist-info/METADATA
pymagotchi-1.1.0.dist-info/WHEEL
pymagotchi-1.1.0.dist-info/entry_points.txt
pymagotchi-1.1.0.dist-info/top_level.txt
pymagotchi-1.1.0.dist-info/RECORD
