Metadata-Version: 2.1
Name: pymagotchi
Version: 1.1.0
Summary: A Python-based virtual pet simulation package with customizable care and stats tracking.
Author-email: book-of-amos <dm6288@nyu.edu>
License: GNU GENERAL PUBLIC LICENSE
Project-URL: Homepage, https://github.com/software-students-fall2024/3-python-package-book-of-amos-1
Project-URL: Repository, https://github.com/software-students-fall2024/3-python-package-book-of-amos-1.git
Project-URL: Bug Tracker, https://github.com/software-students-fall2024/3-python-package-book-of-amos-1/issues
Keywords: virtual pet,simulation,game,pymagotchi,pet care
Classifier: Programming Language :: Python :: 3
Classifier: License :: OSI Approved :: GNU General Public License v3 (GPLv3)
Classifier: Operating System :: OS Independent
Classifier: Topic :: Games/Entertainment :: Simulation
Requires-Python: >=3.7
License-File: LICENSE
Provides-Extra: dev
Requires-Dist: pytest; extra == "dev"
Requires-Dist: freezegun; extra == "dev"
